YALogger/Constants.py
YALogger/__init__.py
YALogger/custom_logger.py
YALogger-1.3.dist-info/METADATA
YALogger-1.3.dist-info/WHEEL
YALogger-1.3.dist-info/top_level.txt
YALogger-1.3.dist-info/RECORD
