Metadata-Version: 2.1
Name: YALogger
Version: 1.3
Summary: Yet Another custom logger
Home-page: https://github.com/DivyenduDutta/YALogger
Author: Divyendu Dutta
Author-email: connect2divyendu@gmail.com
License: UNKNOWN
Platform: UNKNOWN
Classifier: Programming Language :: Python :: 3.7
Classifier: License :: OSI Approved :: GNU General Public License v3 (GPLv3)
Classifier: Operating System :: Microsoft :: Windows
Requires-Python: >=3.7
Requires-Dist: configparser
